dsr_shelx/__init__.py
dsr_shelx/afix.py
dsr_shelx/atomhandling.py
dsr_shelx/atoms.py
dsr_shelx/cf3fit.py
dsr_shelx/constants.py
dsr_shelx/dbfile.py
dsr_shelx/dsr
dsr_shelx/dsr.bat
dsr_shelx/dsr.py
dsr_shelx/dsr_db.txt
dsr_shelx/dsrparse.py
dsr_shelx/elements.py
dsr_shelx/export.py
dsr_shelx/misc.py
dsr_shelx/olex_dsr_db.txt
dsr_shelx/options.py
dsr_shelx/pyperclip.py
dsr_shelx/refine.py
dsr_shelx/resfile.py
dsr_shelx/resi.py
dsr_shelx/restraints.py
dsr_shelx/selfupdate.py
dsr_shelx/sql_export.py
dsr_shelx/terminalsize.py
dsr_shelx/version.py
dsr_shelx/fit/LICENSE.txt
dsr_shelx/fit/__init__.py
dsr_shelx/fit/quatfit.py
dsr_shelx/mpmath/__init__.py
dsr_shelx/mpmath/ctx_base.py
dsr_shelx/mpmath/ctx_fp.py
dsr_shelx/mpmath/ctx_iv.py
dsr_shelx/mpmath/ctx_mp.py
dsr_shelx/mpmath/ctx_mp_python.py
dsr_shelx/mpmath/function_docs.py
dsr_shelx/mpmath/identification.py
dsr_shelx/mpmath/math2.py
dsr_shelx/mpmath/rational.py
dsr_shelx/mpmath/usertools.py
dsr_shelx/mpmath/visualization.py
dsr_shelx/mpmath/calculus/__init__.py
dsr_shelx/mpmath/calculus/approximation.py
dsr_shelx/mpmath/calculus/calculus.py
dsr_shelx/mpmath/calculus/differentiation.py
dsr_shelx/mpmath/calculus/extrapolation.py
dsr_shelx/mpmath/calculus/inverselaplace.py
dsr_shelx/mpmath/calculus/odes.py
dsr_shelx/mpmath/calculus/optimization.py
dsr_shelx/mpmath/calculus/polynomials.py
dsr_shelx/mpmath/calculus/quadrature.py
dsr_shelx/mpmath/functions/__init__.py
dsr_shelx/mpmath/functions/bessel.py
dsr_shelx/mpmath/functions/elliptic.py
dsr_shelx/mpmath/functions/expintegrals.py
dsr_shelx/mpmath/functions/factorials.py
dsr_shelx/mpmath/functions/functions.py
dsr_shelx/mpmath/functions/hypergeometric.py
dsr_shelx/mpmath/functions/orthogonal.py
dsr_shelx/mpmath/functions/qfunctions.py
dsr_shelx/mpmath/functions/rszeta.py
dsr_shelx/mpmath/functions/theta.py
dsr_shelx/mpmath/functions/zeta.py
dsr_shelx/mpmath/functions/zetazeros.py
dsr_shelx/mpmath/libmp/__init__.py
dsr_shelx/mpmath/libmp/backend.py
dsr_shelx-242.dist-info/METADATA
dsr_shelx-242.dist-info/WHEEL
dsr_shelx-242.dist-info/entry_points.txt
dsr_shelx-242.dist-info/RECORD
