Metadata-Version: 2.1
Name: dsr_shelx
Version: 242
Summary: A program to model disorder in small-molecule X-ray structures
Project-URL: Homepage, https://dkratzert.de/dsr.html
Project-URL: Bug Tracker, https://github.com/dkratzert/DSR/issues
Author-email: Daniel Kratzert <dkratzert@gmx.de>
Classifier: Development Status :: 5 - Production/Stable
Classifier: License :: OSI Approved :: MIT License
Classifier: Operating System :: OS Independent
Classifier: Programming Language :: Python :: 3
Classifier: Topic :: Scientific/Engineering :: Chemistry
Requires-Python: >=3.9
